.DS_Store
mangawalk/__init__.py
mangawalk/scraping/__init__.py
mangawalk/scraping/comick.py
mangawalk/scraping/types/__init__.py
mangawalk/scraping/types/type_comick.py
mangawalk/scraping/types/type_mangawalk.py
mangawalk/utils/__init__.py
mangawalk/utils/aws_s3.py
mangawalk/utils/dateutils.py
mangawalk/utils/functional.py
tests/__init__.py
tests/scraping/__init__.py
tests/scraping/test_comick.py
mangawalk-0.1.2.dist-info/METADATA
mangawalk-0.1.2.dist-info/WHEEL
mangawalk-0.1.2.dist-info/top_level.txt
mangawalk-0.1.2.dist-info/RECORD
