Metadata-Version: 2.1
Name: mangawalk
Version: 0.1.2
Summary: Core library for crawling and web scraping
Home-page: https://rescala.jp
Author: rv
Author-email: yo-maruya@rescala.jp
License: MIT
Project-URL: Bug Reports, https://github.com/rv-rescala/mangawalk/issues
Project-URL: Source, https://github.com/rv-rescala/mangawalk
Keywords: python crawler scraping
Platform: UNKNOWN
Requires-Python: >=3.7
Requires-Dist: catswalk
